ffsync/__init__.py
ffsync/__main__.py
ffsync/sync.py
ffsync-0.0.8.dist-info/LICENSE
ffsync-0.0.8.dist-info/WHEEL
ffsync-0.0.8.dist-info/METADATA
ffsync-0.0.8.dist-info/RECORD
